README.md
setup.py
network_bio_toolkit/Heat2.py
network_bio_toolkit/Heat3.py
network_bio_toolkit/PrepGsea.py
network_bio_toolkit/Upstream.py
network_bio_toolkit/__init__.py
network_bio_toolkit/create_graph.py
network_bio_toolkit/heat_and_cluster.py
network_bio_toolkit/stat_analysis.py
network_bio_toolkit.egg-info/PKG-INFO
network_bio_toolkit.egg-info/SOURCES.txt
network_bio_toolkit.egg-info/dependency_links.txt
network_bio_toolkit.egg-info/top_level.txt