Metadata-Version: 1.1
Name: network-bio-toolkit
Version: 0.1.3
Summary: Network Analysis Toolkit
Home-page: https://github.com/ucsd-ccbb/network_bio_toolkit
Author: Mikayla Webster (13webstermj@gmail.com), Mengyi (Miko) Liu (mikoliu798@gmail.com), Brin Rosenthal (sbrosenthal@ucsd.edu)
Author-email: sbrosenthal@ucsd.edu
License: MIT
Keywords: Jupyter notebook,interactive,network
Platform: UNKNOWN
Classifier: License :: OSI Approved :: MIT License
Classifier: Programming Language :: Python :: 2
